orb_cloud_client/__init__.py
orb_cloud_client/client.py
orb_cloud_client/example.py
orb_cloud_client/example_async.py
orb_cloud_client/models/__init__.py
orb_cloud_client/models/config.py
orb_cloud_client/models/db.py
orb_cloud_client/models/generic.py
orb_cloud_client/models/server.py
orb_cloud_client-1.3.2.dist-info/licenses/LICENSE
orb_cloud_client-1.3.2.dist-info/METADATA
orb_cloud_client-1.3.2.dist-info/WHEEL
orb_cloud_client-1.3.2.dist-info/entry_points.txt
orb_cloud_client-1.3.2.dist-info/top_level.txt
orb_cloud_client-1.3.2.dist-info/RECORD
