Metadata-Version: 2.4
Name: orb-cloud-client
Version: 1.3.2
Summary: Python client library for Orb Cloud API
Author-email: Orb Networks <support@orb.net>
License-Expression: MIT
Project-URL: Documentation, https://api.orb.net/docs
Project-URL: Homepage, https://github.com/orbforge/orb-cloud
Project-URL: Repository, https://github.com/orbforge/orb-cloud
Classifier: Development Status :: 4 - Beta
Classifier: Intended Audience :: Developers
Classifier: Programming Language :: Python :: 3
Classifier: Programming Language :: Python :: 3.8
Classifier: Programming Language :: Python :: 3.9
Classifier: Programming Language :: Python :: 3.10
Classifier: Programming Language :: Python :: 3.11
Classifier: Programming Language :: Python :: 3.12
Requires-Python: >=3.8
License-File: LICENSE
Requires-Dist: build>=1.2.2.post1
Requires-Dist: httpx>=0.24.0
Requires-Dist: pydantic>=2.0.0
Requires-Dist: twine>=6.1.0
Provides-Extra: dev
Requires-Dist: build; extra == "dev"
Requires-Dist: pytest; extra == "dev"
Dynamic: license-file
